composable_paxos.py
setup.cfg
setup.py
composable_paxos.egg-info/PKG-INFO
composable_paxos.egg-info/SOURCES.txt
composable_paxos.egg-info/dependency_links.txt
composable_paxos.egg-info/pbr.json
composable_paxos.egg-info/top_level.txt